LICENSE
NOTICE
vexy/__init__.py
vexy/__main__.py
vexy/client.py
vexy/py.typed
vexy/sources/__init__.py
vexy/sources/base.py
vexy/sources/ossindex.py
vexy/sources/osv.py
vexy/sources/osvdb.py
vexy-0.3.1.dist-info/LICENSE
vexy-0.3.1.dist-info/METADATA
vexy-0.3.1.dist-info/WHEEL
vexy-0.3.1.dist-info/entry_points.txt
vexy-0.3.1.dist-info/RECORD
