Metadata-Version: 2.1
Name: vexy
Version: 0.3.1
Summary: Generate VEX (Vulnerability Exploitability Exchange) CycloneDX documents
Home-page: https://github.com/madpah/vexy
License: Apache-2.0
Author: Paul Horton
Author-email: paul.horton@owasp.org
Requires-Python: >=3.7,<4.0
Classifier: Development Status :: 4 - Beta
Classifier: Intended Audience :: Developers
Classifier: Intended Audience :: Information Technology
Classifier: Intended Audience :: Legal Industry
Classifier: Intended Audience :: System Administrators
Classifier: License :: OSI Approved :: Apache Software License
Classifier: Programming Language :: Python :: 3
Classifier: Programming Language :: Python :: 3.7
Classifier: Programming Language :: Python :: 3.8
Classifier: Programming Language :: Python :: 3.9
Classifier: Programming Language :: Python :: 3.10
Classifier: Programming Language :: Python :: 3.11
Classifier: Programming Language :: Python :: 3.10
Classifier: Programming Language :: Python :: 3.7
Classifier: Programming Language :: Python :: 3.8
Classifier: Programming Language :: Python :: 3.9
Classifier: Topic :: Security
Classifier: Topic :: Software Development
Classifier: Topic :: System :: Software Distribution
Classifier: Typing :: Typed
Requires-Dist: cyclonedx-python-lib (>=4.0.0rc1,<5.0.0)
Requires-Dist: importlib-metadata (>=3.4) ; python_version < "3.8"
Requires-Dist: ossindex-lib (>=1.1.1,<2.0.0)
Requires-Dist: osv-lib (>=0.2.1,<0.3.0)
Requires-Dist: packageurl-python (>=0.9)
Requires-Dist: rich (>=12.4.4,<13.0.0)
Project-URL: Repository, https://github.com/madpah/vexy
